{
  "public": {

    "debug": false,

    "title": "The 2020 State of JavaScript Survey",
    "tagline":"Take the State of JavaScript survey",
    "siteImage": "https://survey.stateofjs.com/stateofjs-social.png",

    "environment": "development",
    
    "faviconUrl": "/favicon.png",

    "defaultLocaleId": "en-US",
    "locale": "en-US",

    "host": "lh",
    "hosting": "Localhost",
    "hostingLink": "http://localhost:5000/",
    
    "sentryXXX": {
      "clientDSN": "foobar"
    }
  },

  "defaultEmail": "hello@stateofjs.com",
  "mailUrlXXX": "smtp://foo:foobar@smtp.mailgun.org:587/",

  "sentryXXX": {
    "serverDSN": "foobar"
  },

  "translationAPIXXX": "http://localhost:4000/graphql",

  "translationAPI": "http://api.stateofjs.com/graphql",

  "apiKeyXXX": "foobar",
  
  "encriptionKeyXXX": "foobar",

  "disableAPICache": true
}
